<?xml version="1.0" encoding="UTF-8"?>
<!DOCTYPE mapper
  PUBLIC "-//mybatis.org//DTD Mapper 3.0//EN"
  "http://mybatis.org/dtd/mybatis-3-mapper.dtd">
<mapper namespace="my">

	<select id="countMypj" parameterType="projectDTO" resultType="int">
		select count(*) from project where code = #{code} and userId=#{userId}
	</select>

	<select id="countMytopic" parameterType="topicDTO" resultType="int">
		select count(*) from topic where code = #{code} and userId=#{userId}
	</select>
	
	<select id="selectMypjlist" parameterType="hashmap" resultType="projectDTO">
		<![CDATA[
		select B.* from 
			(select A.*, rownum r from 
				(select * from project where userId=#{userId} and code=#{code} order by proNum desc) A 
			order by proNum desc) B
		where r >= #{start} and r <= #{end}
		]]>
	</select>
	
	<select id="selectMytopiclist" parameterType="hashmap" resultType="topicDTO">
		<![CDATA[
		select B.* from 
			(select A.*, rownum r from 
				(select * from topic where userId=#{userId} and code=#{code} order by topNum desc) A 
			order by topNum desc) B
		where r >= #{start} and r <= #{end}
		]]>
	</select>
	
	<select id="countMytopicComm" parameterType="hashmap" resultType="int">
		select count(*) from topcomments where code = #{code} and userId=#{userId}
	</select>
	
	<select id="selectMytopicCommlist" parameterType="hashmap" resultType="topCommDTO">
		<![CDATA[
		select B.* from 
			(select A.*, rownum r from        
				(SELECT t.topTitle, c.* FROM topic t, topComments c WHERE  c.code = #{code} and c.userId=#{userId} and t.topNum = c.topnum) A 
			order by a.topcomnum desc) B
		where r >= #{start} and r <= #{end}
		]]>
	</select>
	
	<select id="selectUserInfo" parameterType="hashmap" resultType="userInfoDTO">
		select b.bizName, u.name, u.email, u.tel, u.dept, u.position from business b, users u where b.code = u.code and u.userId=#{userId} and u.code=#{code}
	</select>
	
	<update id="UpdateUser" parameterType="hashmap">
		update users set email=#{email}, tel=#{tel} where userId=#{userId}
	</update>
	
	<select id="idPwCheck" parameterType="hashmap" resultType="int">
		select count(*) from users where userId=#{userId} and pw=#{pw}
	</select>
	
	<update id="updatePw" parameterType="hashmap">
		update users set pw=#{pw} where userId=#{userId}
	</update>
	
	<delete id="deleteUser" parameterType="String">
		delete from users where userId=#{value}
	</delete>
	
</mapper> 